model_registry_python_sdk/__init__.py
model_registry_python_sdk/client.py
rhods_model_registry_poc-0.1.13.dist-info/METADATA
rhods_model_registry_poc-0.1.13.dist-info/WHEEL
rhods_model_registry_poc-0.1.13.dist-info/RECORD
