Metadata-Version: 2.1
Name: rhods-model-registry-poc
Version: 0.1.13
Summary: 
Author: Andrea Peruffo
Author-email: andrea.peruffo1982@gmail.com
Requires-Python: >=3.9,<4.0
Classifier: Programming Language :: Python :: 3
Classifier: Programming Language :: Python :: 3.9
Classifier: Programming Language :: Python :: 3.10
Classifier: Programming Language :: Python :: 3.11
Requires-Dist: apicurio-registry-python-sdk-preview (>=2.4.14,<3.0.0)
Requires-Dist: minio (>=7.1.14,<8.0.0)
